all_files_reader/__init__.py
all_files_reader/filereader.py
AllFilesReader-0.0.14.dist-info/LICENSE
AllFilesReader-0.0.14.dist-info/METADATA
AllFilesReader-0.0.14.dist-info/WHEEL
AllFilesReader-0.0.14.dist-info/top_level.txt
AllFilesReader-0.0.14.dist-info/RECORD
